bkstools/__init__.py
bkstools/release.py
bkstools/bks_lib/__init__.py
bkstools/bks_lib/bks_base.py
bkstools/bks_lib/bks_base_common.py
bkstools/bks_lib/bks_ble.py
bkstools/bks_lib/bks_firmware_enums.py
bkstools/bks_lib/bks_gui.py
bkstools/bks_lib/bks_http.py
bkstools/bks_lib/bks_modbus.py
bkstools/bks_lib/bks_module.py
bkstools/bks_lib/bks_options.py
bkstools/bks_lib/debug.py
bkstools/bks_lib/hms.py
bkstools/bks_lib/hsm_enums.py
bkstools/demo/__init__.py
bkstools/demo/demo_bks_grip_outside_inside.py
bkstools/demo/demo_diagnostics.py
bkstools/demo/demo_grip_workpiece_with_expected_position.py
bkstools/demo/demo_interrupt_movement.py
bkstools/demo/demo_modbus.py
bkstools/demo/demo_read_exception_status.py
bkstools/demo/demo_repeat_commmand.py
bkstools/demo/demo_simple.py
bkstools/scripts/MF_28585_reproduce.py
bkstools/scripts/MF_30833_reproduce.py
bkstools/scripts/__init__.py
bkstools/scripts/bks.py
bkstools/scripts/bks_get_system_messages.py
bkstools/scripts/bks_grip.py
bkstools/scripts/bks_jog.py
bkstools/scripts/bks_move.py
bkstools/scripts/bks_ref.py
bkstools/scripts/bks_scan.py
bkstools/scripts/bks_status.py
bkstools/scripts/sil_com_test.py
bkstools-0.0.2.31.data/data/cmd-here.lnk
bkstools-0.0.2.31.data/data/bkstools_data/default_settings.bak
bkstools-0.0.2.31.data/data/bkstools_data/default_settings.dat
bkstools-0.0.2.31.data/data/bkstools_data/default_settings.dir
pyschunk/__init__.py
pyschunk/release.py
pyschunk/generated/generated_enums.py
pyschunk/generated/generated_parameters.py
pyschunk/guistuff/__init__.py
pyschunk/guistuff/ci.py
pyschunk/guistuff/colors.py
pyschunk/guistuff/fonts.py
pyschunk/guistuff/sound.py
pyschunk/guistuff/test_widgets.py
pyschunk/guistuff/tooltip.py
pyschunk/guistuff/tutorial.py
pyschunk/guistuff/unisymbols.py
pyschunk/guistuff/widgets.py
pyschunk/guistuff/pic/ci1.gif
pyschunk/guistuff/pic/ci2.gif
pyschunk/guistuff/pic/down.gif
pyschunk/guistuff/pic/down_disabled.gif
pyschunk/guistuff/pic/left.gif
bkstools-0.0.2.31.dist-info/LICENSE.txt
bkstools-0.0.2.31.dist-info/METADATA
bkstools-0.0.2.31.dist-info/WHEEL
bkstools-0.0.2.31.dist-info/entry_points.txt
bkstools-0.0.2.31.dist-info/top_level.txt
bkstools-0.0.2.31.dist-info/RECORD
