Metadata-Version: 2.1
Name: bkstools
Version: 0.0.2.31
Summary: bkstools: Tools to interact with SCHUNK BKS grippers via the HTTP/JSON webinterface or Modbus-RTU
Home-page: https://github.com/SCHUNK-SE-Co-KG/bkstools.git
Download-URL: https://github.com/SCHUNK-SE-Co-KG/bkstools/archive/refs/tags/0.0.2.31_2024-06-24.tar.gz
Author: Dirk Osswald
Author-email: dirk.osswald@de.schunk.com
License: GPL v3
Keywords: SCHUNK gripper BKS EGI EGU EGK
Classifier: Development Status :: 4 - Beta
Classifier: Intended Audience :: End Users/Desktop
Classifier: Topic :: Scientific/Engineering :: Human Machine Interfaces
Classifier: License :: OSI Approved :: GNU General Public License v3 (GPLv3)
Classifier: Programming Language :: Python :: 3
Classifier: Programming Language :: Python :: 3.10
Requires-Python: >=3
License-File: LICENSE.txt
Requires-Dist: requests >=2.26.0
Requires-Dist: PyYAML >=5.4.1
Requires-Dist: minimalmodbus >=2.0.1
Requires-Dist: wrapt
Requires-Dist: pypiwin32 ; platform_system == "Windows"
